README.rst
setup.py
sniprd.egg-info/PKG-INFO
sniprd.egg-info/SOURCES.txt
sniprd.egg-info/dependency_links.txt
sniprd.egg-info/not-zip-safe
sniprd.egg-info/requires.txt
sniprd.egg-info/top_level.txt
source/snip
source/sniprd/__init__.py
source/sniprd/_version.py
source/sniprd/sniprepo.py
source/sniprd/utils.py