Metadata-Version: 1.1
Name: sniprd
Version: 0.1.1.1
Summary: Status Report - Comfortable CLI Activity Status Reporting
Home-page: https://github.com/kejably2/sniprd
Author: Chris Ward
Author-email: cward@redhat.com
License: GPLv2
Download-URL: https://github.com/kejably2/sniprd/archive/master.zip
Keywords: information,postgresql,tasks,snippets
Platform: UNKNOWN
Classifier: License :: OSI Approved :: GNU General Public License v3 (GPLv3)
Classifier: Natural Language :: English
Classifier: Programming Language :: Python :: 2.7
Classifier: Topic :: Office/Business
Classifier: Topic :: Utilities
Provides: sniprd
